better_safe_than_sorry/README.md
better_safe_than_sorry/__init__.py
better_safe_than_sorry/analysis/README.md
better_safe_than_sorry/analysis/__init__.py
better_safe_than_sorry/analysis/main.py
better_safe_than_sorry/generation_of_test_profiles/README.md
better_safe_than_sorry/generation_of_test_profiles/__init__.py
better_safe_than_sorry/generation_of_test_profiles/main.py
better_safe_than_sorry/generation_of_test_profiles/random_test_generator.py
better_safe_than_sorry/shared/__init__.py
better_safe_than_sorry/simulation/README.md
better_safe_than_sorry/simulation/__init__.py
better_safe_than_sorry/simulation/analyze.py
better_safe_than_sorry/simulation/breaking_rules_randomizer.py
better_safe_than_sorry/simulation/simulate.py
better_safe_than_sorry/utils/__init__.py
better_safe_than_sorry/utils/custom_export.py
better_safe_than_sorry/utils/custom_logging.py
better_safe_than_sorry/vagrant_deployment/README.md
better_safe_than_sorry/vagrant_deployment/__init__.py
better_safe_than_sorry/vagrant_deployment/main.py
better_safe_than_sorry-0.1.2.dist-info/entry_points.txt
better_safe_than_sorry-0.1.2.dist-info/LICENSE
better_safe_than_sorry-0.1.2.dist-info/WHEEL
better_safe_than_sorry-0.1.2.dist-info/METADATA
better_safe_than_sorry-0.1.2.dist-info/RECORD
