Metadata-Version: 2.1
Name: better-safe-than-sorry
Version: 0.1.2
Summary: 
Author: Michael Sammereier
Author-email: michael.sammereier@tum.de
Maintainer: Patrick Stöckle
Maintainer-email: patrick.stoeckle@tum.de
Requires-Python: >=3.7,<4.0
Classifier: Programming Language :: Python :: 3
Classifier: Programming Language :: Python :: 3.7
Classifier: Programming Language :: Python :: 3.8
Classifier: Programming Language :: Python :: 3.9
Classifier: Programming Language :: Python :: 3.10
Requires-Dist: pyeda (==0.28.0)
Requires-Dist: scikit-learn (>=1.0.1,<2.0.0)
Requires-Dist: typer (>=0.6.1,<0.7.0)
